{
    "images": [
        "https://sf-maas-uat-prod.oss-cn-shanghai.aliyuncs.com/outputs/f70eea77-0e79-4e3b-8fcc-7fd2430fe735_0.png",
        "https://sf-maas-uat-prod.oss-cn-shanghai.aliyuncs.com/outputs/fddc64c5-09b2-493b-add0-dd8a9c4a5e4b_0.png",
        "https://sf-maas-uat-prod.oss-cn-shanghai.aliyuncs.com/outputs/34f05f71-5005-4385-b385-70684c2034fc_0.png"
    ],
    "content": "剧辛乐毅感恩分，输肝剖胆效英才。",
    "origin": "行路难三首",
    "author": "李白",
    "category": "古诗文-抒情-感恩",
    "date": "2024/11/30 18:46:46",
    "localImagesPath": "1732963606765"
}